{
    "title": "Porca Vacca",
    "carousel_1": "../images/games/PorcaVacca_A.webp",
    "carousel_2": "../images/games/PorcaVacca_B.webp",
    "carousel_3": "../images/games/PorcaVacca_C.webp",
    "description": "Vi piace la carne, le griglie, le risate e la compagnia? <b>Porca Vacca</b> è quello che fa per voi.<br><br>Questo gioco di carte è adatto a tutti e porterà l'acquilina in bocca a tutti i partecipenti; lo scopo del gioco è quello di restare con meno di cinque carte in mano alla fine del prorpio turno cercando di difendervi da mucche pazze ed attaccando gli avversari con succolentissimi tagli di Chianina.<br><br>Diego Grigolin",
    "players": "3-8",
    "time": "20 min",
    "producer": "House of Games",
    "type": "Gioco di Carte, Competitivo"
}